{
    "DNDConfig": null,
    "__parentReadjusting__": false,
    "_height_": {
        "type": "ref",
        "value": "preferred"
    },
    "_left_": {
        "type": "string",
        "value": "0dp"
    },
    "_margin_": [
        0,
        0,
        0,
        0
    ],
    "_orientation_": 6,
    "_padding_": [
        0,
        0,
        0,
        0
    ],
    "_percent_": true,
    "_skin_": "s2a016ad20de42e9858c145b4fde0e87",
    "_top_": {
        "type": "string",
        "value": "15%"
    },
    "_width_": {
        "type": "string",
        "value": "100%"
    },
    "allboxes": [],
    "autogrowmode": 1,
    "canUpdateUI": true,
    "children": [
        "CopyLabel09ee356d4cf4d4d"
    ],
    "clipbounds": true,
    "containerweight": 100,
    "enablescrolling": true,
    "id": "FlexContainerRecommendationNoFeilds",
    "info": null,
    "isvisible": true,
    "kuid": "b2a1660b303d4c47b4a2286e0b6af468",
    "layouttype": 2,
    "name": "kony.ui.FlexContainer",
    "parent": "TestRecommendTab",
    "pf": "frmAdmitForm",
    "snapgridsize": 10,
    "snaptogrid": true,
    "tabpaneId": "admitFormTabSection",
    "vizProps": {
        "hide": true
    },
    "wType": "FlexContainer",
    "widgetalignment": 1,
    "zindex": 1
}