{
    "@class": "com.kony.gen.viz.model.component.KVizLabel",
    "DNDConfig": null,
    "__parentReadjusting__": false,
    "_height_": {
        "type": "ref",
        "value": "preferred"
    },
    "_left_": {
        "type": "string",
        "value": "0dp"
    },
    "_margin_": [
        1,
        1,
        1,
        1
    ],
    "_padding_": [
        0,
        0,
        0,
        0
    ],
    "_skin_": "s609f512e6f7466c828b7ddbcd3dfee2",
    "_text_": "*",
    "_top_": {
        "type": "string",
        "value": "-2dp"
    },
    "_width_": {
        "type": "ref",
        "value": "preferred"
    },
    "_wrapping_": 2,
    "android": {
        "textStyle": {
            "letterSpacing": 0,
            "strikeThrough": false
        }
    },
    "canUpdateUI": true,
    "containerweight": 100,
    "contentalignment": 4,
    "id": "Label0443da55fb2f945",
    "info": null,
    "ipad": {
        "psp": {
            "wrapping": 2
        }
    },
    "iphone": {
        "psp": {
            "wrapping": 2
        }
    },
    "isvisible": true,
    "kuid": "e013066634534027a782e867115cb7ed",
    "name": "kony.ui.Label",
    "parent": "FlexContainer030961230942f49",
    "pf": "frmAdmitForm",
    "tabpaneId": "admitFormTabSection",
    "tooltip": "",
    "wType": "Label",
    "zindex": 1
}