{
    "__parentReadjusting__": false,
    "_padding_": [
        0,
        0,
        0,
        0
    ],
    "_skin_": "s6f58fa3350b43f599c3844f4d87d7a6",
    "_srcKuid_": "m701de5eec48478897fe9afbea73e955",
    "areflexpropsreferenced": true,
    "canUpdateUI": true,
    "channel": "mobile",
    "context": {},
    "dataDiffs": {},
    "id": "labelAlerttoneSettings",
    "instanceOf": "m701de5eec48478897fe9afbea73e955",
    "isdatareferenced": true,
    "isvisible": true,
    "kuid": "m7f89cee893545f0b2aa3353a5e3cc4b",
    "masterInstance": true,
    "name": "kony.ui.Label",
    "parent": "flxAlerttoneSettings",
    "pf": "frmSupport",
    "wType": "Label"
}